{
  "lesson_id": "lesson04",
  "cluster": "mo",
  "cluster_meaning": "food and drink",
  "rounds": [
    {
      "round": 1,
      "title": "Round 1",
      "buckets": ["mol"],
      "words_per_bucket": 3
    },
    {
      "round": 2,
      "title": "Round 2",
      "buckets": ["moa"],
      "words_per_bucket": 3
    },
    {
      "round": 3,
      "title": "Round 3",
      "buckets": ["moa", "mol"],
      "words_per_bucket": 3,
      "allow_repeats": true
    },
    {
      "round": 4,
      "title": "Round 4",
      "buckets": ["mo_other"],
      "words_per_bucket": 3
    },
    {
      "round": 5,
      "title": "Round 5",
      "buckets": ["mo_on"],
      "words_per_bucket": 3
    },
    {
      "round": 6,
      "title": "Round 6",
      "buckets": ["mo_other", "mo_on"],
      "words_per_bucket": 3,
      "allow_repeats": true
    }
  ],
  "words": [
    {
      "id": "mo_l1",
      "oravia": "molban",
      "english": "cup",
      "bucket": "mol"
    },
    {
      "id": "mo_l2",
      "oravia": "molcui",
      "english": "bowl",
      "bucket": "mol"
    },
    {
      "id": "mo_l3",
      "oravia": "molvou",
      "english": "bottle",
      "bucket": "mol"
    },
    {
      "id": "mo_a1",
      "oravia": "moaria",
      "english": "apple",
      "bucket": "moa"
    },
    {
      "id": "mo_a2",
      "oravia": "moale",
      "english": "banana",
      "bucket": "moa"
    },
    {
      "id": "mo_a3",
      "oravia": "moanih",
      "english": "berry",
      "bucket": "moa"
    },
    {
      "id": "mo_o1",
      "oravia": "mogali",
      "english": "coffee",
      "bucket": "mo_other"
    },
    {
      "id": "mo_o2",
      "oravia": "mouje",
      "english": "drink",
      "bucket": "mo_other"
    },
    {
      "id": "mo_o3",
      "oravia": "mocen",
      "english": "chocolate",
      "bucket": "mo_other"
    },
    {
      "id": "mo_on1",
      "oravia": "moyi",
      "english": "sugar",
      "bucket": "mo_on"
    },
    {
      "id": "mo_on2",
      "oravia": "moyame",
      "english": "spice",
      "bucket": "mo_on"
    },
    {
      "id": "mo_on3",
      "oravia": "moval",
      "english": "ice",
      "bucket": "mo_on"
    }
  ]
}
